{
  "parent": "bonesupdate:root",
  "criteria": {
    "weeping_willow_tree": {
      "conditions": {
        "player": [
          {
            "condition": "minecraft:entity_properties",
            "entity": "this",
            "predicate": {
              "location": {
                "structure": "bonesupdate:weeping_willow_tree"
              }
            }
          }
        ]
      },
      "trigger": "minecraft:location"
    }
  },
  "display": {
    "announce_to_chat": true,
    "description": {
      "translate": "advancements.necromancy.find_weeping_willow_tree.description"
    },
    "frame": "task",
    "hidden": false,
    "icon": {
      "count": 1,
      "id": "bonesupdate:weeping_willow_vines"
    },
    "show_toast": true,
    "title": {
      "translate": "advancements.necromancy.find_weeping_willow_tree.title"
    }
  },
  "requirements": [
    [
      "weeping_willow_tree"
    ]
  ]
}